databaseRestoreIntegrity/__init__.py
databaseRestoreIntegrity/mysqldb.py
databaseRestoreIntegrity/postgresdb.py
databaseRestoreIntegrity-1.1.2.dist-info/LICENSE.txt
databaseRestoreIntegrity-1.1.2.dist-info/METADATA
databaseRestoreIntegrity-1.1.2.dist-info/WHEEL
databaseRestoreIntegrity-1.1.2.dist-info/top_level.txt
databaseRestoreIntegrity-1.1.2.dist-info/RECORD
