Metadata-Version: 2.1
Name: databaseRestoreIntegrity
Version: 1.1.2
Summary: A package to check mysql restore integrity check
Home-page: 
Author: Maihraj Hasan
Author-email: maihrajhasan@gmail.com
Project-URL: Bug Tracker, https://github.com/maihraj/Python3/mysqlRestoreIntegrityCheck/-/issues
Project-URL: repository, https://github.com/maihraj/Python3/mysqlRestoreIntegrityCheck
Classifier: Programming Language :: Python :: 3
Classifier: License :: OSI Approved :: MIT License
Classifier: Operating System :: OS Independent
Requires-Python: >=3.6
License-File: LICENSE.txt
